{
  "id": "comp_5",
  "name": "SG90 模拟舵机",
  "type": "PWM",
  "category": "Actuator",
  "pinsUsed": 1,
  "voltage": "5V",
  "active": true,
  "description": "50Hz 单片机 PWM 频率占空比电机",
  "macroPrefix": "SERVO",
  "cadLayout": {
    "width": 160,
    "height": 90,
    "renderType": "generic_board",
    "pins": [
      {
        "name": "VCC",
        "offsetY": 18,
        "type": "VCC"
      },
      {
        "name": "GND",
        "offsetY": 45,
        "type": "GND"
      },
      {
        "name": "PWM",
        "offsetY": 72,
        "type": "PWM"
      }
    ]
  },
  "drivers": {
    "platformioLibs": [],
    "includes": [
      "#include <ESP32Servo.h>"
    ],
    "defines": [],
    "globalInstantiation": "Servo myservo;",
    "setupCode": "myservo.attach(PIN_{{MACRO_PREFIX}});",
    "apiDocumentation": "void write(int value); - 写入引脚角度值（0-180度）"
  }
}